{
  "id": "navigation_item",
  "type": "SharedSlice",
  "name": "NavigationItem",
  "description": "NavigationItem",
  "variations": [
    {
      "id": "default",
      "name": "Default",
      "docURL": "...",
      "version": "initial",
      "description": "Default",
      "imageUrl": "",
      "primary": {
        "company_logo": {
          "type": "Image",
          "config": {
            "label": "Company logo",
            "constraint": {},
            "thumbnails": []
          }
        },
        "company_name": {
          "type": "Text",
          "config": {
            "label": "Company name",
            "placeholder": ""
          }
        },
        "description": {
          "type": "Text",
          "config": {
            "label": "description",
            "placeholder": ""
          }
        },
        "button_text": {
          "type": "Text",
          "config": {
            "label": "Button Text",
            "placeholder": ""
          }
        },
        "button_link": {
          "type": "Link",
          "config": {
            "label": "Button Link",
            "placeholder": "",
            "select": null
          }
        },
        "button_icon": {
          "type": "Image",
          "config": {
            "label": "Button Icon",
            "constraint": {},
            "thumbnails": []
          }
        }
      },
      "items": {
        "name": {
          "type": "Text",
          "config": {
            "label": "name",
            "placeholder": ""
          }
        },
        "link": {
          "type": "Link",
          "config": {
            "label": "link",
            "placeholder": "",
            "select": null
          }
        }
      }
    },
    {
      "id": "blackVariation",
      "name": "blackVariation",
      "docURL": "...",
      "version": "initial",
      "description": "Default",
      "imageUrl": "",
      "primary": {
        "company_logo": {
          "type": "Image",
          "config": {
            "label": "Company logo",
            "constraint": {},
            "thumbnails": []
          }
        },
        "company_name": {
          "type": "Text",
          "config": {
            "label": "Company name",
            "placeholder": ""
          }
        },
        "description": {
          "type": "Text",
          "config": {
            "label": "description",
            "placeholder": ""
          }
        },
        "button_text": {
          "type": "Text",
          "config": {
            "label": "Button Text",
            "placeholder": ""
          }
        },
        "button_icon": {
          "type": "Image",
          "config": {
            "label": "Button Icon",
            "constraint": {},
            "thumbnails": []
          }
        },
        "button_link": {
          "type": "Link",
          "config": {
            "label": "Button Link",
            "placeholder": "",
            "select": null
          }
        }
      },
      "items": {
        "name": {
          "type": "Text",
          "config": {
            "label": "name",
            "placeholder": ""
          }
        },
        "link": {
          "type": "Link",
          "config": {
            "label": "link",
            "placeholder": "",
            "select": null
          }
        }
      }
    }
  ]
}